daisybell/__init__.py
daisybell/__main__.py
daisybell/daisybell.py
daisybell/helpers/__init__.py
daisybell/helpers/chat.py
daisybell/helpers/common.py
daisybell/helpers/dataset.py
daisybell/scanners/README.md
daisybell/scanners/__init__.py
daisybell/scanners/chatbot_ai_alignment.py
daisybell/scanners/masking_language_bias.py
daisybell/scanners/ner_language_bias.py
daisybell/scanners/scanner.py
daisybell/scanners/zero_shot_language_bias.py
daisybell-0.4.4.dist-info/LICENSE
daisybell-0.4.4.dist-info/METADATA
daisybell-0.4.4.dist-info/WHEEL
daisybell-0.4.4.dist-info/entry_points.txt
daisybell-0.4.4.dist-info/RECORD
