Metadata-Version: 2.1
Name: daisybell
Version: 0.4.4
Summary: A scanner that will scan your AI models for problems. Currently it focuses on bias testing. It is currently alpha.
License: Apache-2.0
Author: Your Name
Author-email: you@example.com
Requires-Python: >=3.8,<3.13
Classifier: Development Status :: 3 - Alpha
Classifier: Intended Audience :: Developers
Classifier: Intended Audience :: Science/Research
Classifier: License :: OSI Approved :: Apache Software License
Classifier: Operating System :: OS Independent
Classifier: Programming Language :: Python :: 3
Classifier: Programming Language :: Python :: 3.8
Classifier: Programming Language :: Python :: 3.9
Classifier: Programming Language :: Python :: 3.10
Classifier: Programming Language :: Python :: 3.11
Classifier: Programming Language :: Python :: 3.12
Classifier: Programming Language :: Python :: 3 :: Only
Classifier: Topic :: Scientific/Engineering :: Artificial Intelligence
Provides-Extra: test
Requires-Dist: black[test] (>=24.3.0,<25.0.0) ; extra == "test"
Requires-Dist: dataframe-image (>=0.2.2,<0.3.0)
Requires-Dist: datasets (>=2.20.0,<3.0.0)
Requires-Dist: grpcio (<1.64.2)
Requires-Dist: pandas (>=2.0.2,<3.0.0)
Requires-Dist: pdbpp[test] (>=0.10.3,<0.11.0) ; extra == "test"
Requires-Dist: protobuf (>=5.27.2,<6.0.0)
Requires-Dist: pyright (==1.1.370) ; extra == "test"
Requires-Dist: pysbd (>=0.3.4,<0.4.0)
Requires-Dist: pytest-cov[test] (==5.0.0) ; extra == "test"
Requires-Dist: pytest[test] (==8.2.2) ; extra == "test"
Requires-Dist: ruff[test] (>=0.5.1,<0.6.0) ; extra == "test"
Requires-Dist: sentencepiece (>=0.2.0,<0.3.0)
Requires-Dist: seqeval (>=1.2.2,<2.0.0)
Requires-Dist: tabulate (>=0.9.0,<0.10.0)
Requires-Dist: tensorboard (>=2.13.0,<3.0.0)
Requires-Dist: torch (==2.3.1)
Requires-Dist: transformers (>=4.42.3,<5.0.0)
Requires-Dist: types-tabulate (>=0.9.0.3,<0.10.0.0)
